uuid_utils-0.11.0.dist-info/METADATA
uuid_utils-0.11.0.dist-info/WHEEL
uuid_utils-0.11.0.dist-info/licenses/LICENSE.md
uuid_utils/__init__.py
uuid_utils/__init__.pyi
uuid_utils/_uuid_utils.pypy39-pp73-darwin.so
uuid_utils/compat/__init__.py
uuid_utils/compat/__init__.pyi
uuid_utils/py.typed
uuid_utils-0.11.0.dist-info/RECORD
